{
  "collectionName": "components_contact_us_reach_us_cards",
  "info": {
    "displayName": "ReachUsCards"
  },
  "options": {},
  "attributes": {
    "Title": {
      "type": "string"
    },
    "Description1Grey": {
      "type": "text"
    },
    "Description2Red": {
      "type": "string"
    },
    "Image": {
      "allowedTypes": [
        "images"
      ],
      "type": "media",
      "multiple": false
    },
    "LinkText": {
      "type": "string"
    },
    "LinkUrl": {
      "type": "string"
    }
  }
}
